README.md
license.txt
setup.py
myPackageTFIMMnew/DLA34.py
myPackageTFIMMnew/DPN92.py
myPackageTFIMMnew/InceptionV3.py
myPackageTFIMMnew/ResNeXt.py
myPackageTFIMMnew/VisionTransformer.py
myPackageTFIMMnew/Xception.py
myPackageTFIMMnew/__init__.py
myPackageTFIMMnew/all_models.py
myPackageTFIMMnew/efficient_net_b0.py
myPackageTFIMMnew/importLayers.py
myPackageTFIMMnew/main.py
myPackageTFIMMnew.egg-info/PKG-INFO
myPackageTFIMMnew.egg-info/SOURCES.txt
myPackageTFIMMnew.egg-info/dependency_links.txt
myPackageTFIMMnew.egg-info/top_level.txt